beaapi/__init__.py
beaapi/api_request.py
beaapi/beaapi_error.py
beaapi/get_data.py
beaapi/get_data_set_list.py
beaapi/get_parameter_list.py
beaapi/get_parameter_values.py
beaapi/get_parameter_values_filtered.py
beaapi/get_row_data_value.py
beaapi/py.typed
beaapi/response_to_dict.py
beaapi/response_to_table.py
beaapi/search_metadata.py
beaapi/throttling_caller.py
beaapi/update_metadata.py
beaapi-0.1.0.dist-info/LICENSE
beaapi-0.1.0.dist-info/LICENSE.note
beaapi-0.1.0.dist-info/METADATA
beaapi-0.1.0.dist-info/WHEEL
beaapi-0.1.0.dist-info/top_level.txt
beaapi-0.1.0.dist-info/RECORD
