Metadata-Version: 2.1
Name: beaapi
Version: 0.1.0
Summary: BEA API Python package
Author-email: Bureau of Economic Analysis <developers@bea.gov>
License: CC0
Project-URL: Homepage, https://github.com/us-bea/beaapi
Project-URL: Bug Tracker, https://github.com/us-bea/beaapi/issues
Classifier: Development Status :: 4 - Beta
Classifier: Intended Audience :: Education
Classifier: Intended Audience :: Financial and Insurance Industry
Classifier: Intended Audience :: Science/Research
Classifier: Programming Language :: Python :: 3
Classifier: Operating System :: MacOS :: MacOS X
Classifier: Operating System :: Microsoft :: Windows
Classifier: License :: Public Domain
Requires-Python: >=3.9
License-File: LICENSE
License-File: LICENSE.note
Requires-Dist: pandas
Provides-Extra: dev
Requires-Dist: build ; extra == 'dev'
Requires-Dist: setuptools ; extra == 'dev'
Requires-Dist: setuptools-scm ; extra == 'dev'
Requires-Dist: wheel ; extra == 'dev'
Requires-Dist: jupyter ; extra == 'dev'
Requires-Dist: python-dotenv ; extra == 'dev'
Requires-Dist: nbconvert ; extra == 'dev'
Requires-Dist: sphinx ; extra == 'dev'
Requires-Dist: nbsphinx ; extra == 'dev'
Requires-Dist: pandoc ; extra == 'dev'
Requires-Dist: unittest ; extra == 'dev'
Requires-Dist: flake8 ; extra == 'dev'
Requires-Dist: mypy ; extra == 'dev'
Requires-Dist: twine ; extra == 'dev'
